src/tweet_service.py
iflow_mcp_mcp_twitter-0.1.0.dist-info/METADATA
iflow_mcp_mcp_twitter-0.1.0.dist-info/WHEEL
iflow_mcp_mcp_twitter-0.1.0.dist-info/entry_points.txt
iflow_mcp_mcp_twitter-0.1.0.dist-info/RECORD
