Metadata-Version: 2.4
Name: iflow-mcp_mcp-twitter
Version: 0.1.0
Summary: Twitter MCP Server - Manage Twitter account programmatically with MCP tools
Author-email: IFLOW <iflow@example.com>
Requires-Python: >=3.8
Requires-Dist: mcp
Requires-Dist: python-dotenv
Requires-Dist: twikit
